zensols/alsum/__init__.py
zensols/alsum/app.py
zensols/alsum/cli.py
zensols/alsum/graph.py
zensols/alsum/resources/app.conf
zensols/alsum/resources/default.conf
zensols/alsum/resources/obj.yml
zensols.alsum-0.0.1.dist-info/METADATA
zensols.alsum-0.0.1.dist-info/WHEEL
zensols.alsum-0.0.1.dist-info/entry_points.txt
zensols.alsum-0.0.1.dist-info/top_level.txt
zensols.alsum-0.0.1.dist-info/RECORD
