Metadata-Version: 2.2
Name: zensols.alsum
Version: 0.0.1
Summary: Summarize text using Component ALignment Abstract Meaning Representation (CALAMR) alignment.
Home-page: https://github.com/plandes/alsum
Download-URL: https://github.com/plandes/alsum/releases/download/v0.0.1/zensols.alsum-0.0.1-py3-none-any.whl
Author: Paul Landes
Author-email: landes@mailc.net
Keywords: tooling
Requires-Dist: zensols.calamr~=0.1.0
Dynamic: author
Dynamic: author-email
Dynamic: description
Dynamic: description-content-type
Dynamic: download-url
Dynamic: home-page
Dynamic: keywords
Dynamic: requires-dist
Dynamic: summary
